kjf/__init__.py
kjf/demo.py
kjf/run_ctp.py
kjf/run_ib.py
kjf/test.py
kjf/strategies/__init__.py
kjf/strategies/k_minute_ib.py
kjf/strategies/k_monitor_0103.py
kjf-0.1.202403.8.dist-info/LICENSE
kjf-0.1.202403.8.dist-info/METADATA
kjf-0.1.202403.8.dist-info/WHEEL
kjf-0.1.202403.8.dist-info/top_level.txt
kjf-0.1.202403.8.dist-info/RECORD
