Metadata-Version: 2.1
Name: kjf
Version: 0.1.202403.8
Summary: Software plugins for EGOPY platform 
Home-page: https://pypi.org/project/kjf
Author: KJF
License: The BSD 3-Clause License
Classifier: Operating System :: POSIX :: Linux
Classifier: Programming Language :: Python :: 3
Classifier: Programming Language :: C
Classifier: Topic :: Office/Business :: Financial
Classifier: Topic :: Scientific/Engineering :: Mathematics
Classifier: License :: OSI Approved :: BSD License
Classifier: Natural Language :: Chinese (Simplified)
Requires-Python: <3.11,>=3.10
License-File: LICENSE
